CHANGELOG.txt
LICENCE.txt
MANIFEST.in
README.rst
README.txt
setup.py
pythonsemver/__init__.py
pythonsemver.egg-info/PKG-INFO
pythonsemver.egg-info/SOURCES.txt
pythonsemver.egg-info/dependency_links.txt
pythonsemver.egg-info/top_level.txt