Metadata-Version: 1.1
Name: pythonsemver
Version: 0.0.1
Summary: this is used for redirection by lambda edge and for semantic-versioning
Home-page: https://github.com/chakri1998/npmsemver
Author: Devarakonda Chakradhar
Author-email: chakradhar1998@outlook.com
License: MIT
Keywords: semantic-versioning,lambda edge url redirection
Platform: UNKNOWN
Classifier: Development Status :: 5 - Production/Stable
Classifier: Intended Audience :: Education
Classifier: Operating System :: Microsoft :: Windows :: Windows 10
Classifier: License :: OSI Approved :: MIT License
Classifier: Programming Language :: Python :: 3
